time_server.py
cuc_mcp_time_server-0.1.0.dist-info/licenses/LICENSE
cuc_mcp_time_server-0.1.0.dist-info/METADATA
cuc_mcp_time_server-0.1.0.dist-info/WHEEL
cuc_mcp_time_server-0.1.0.dist-info/entry_points.txt
cuc_mcp_time_server-0.1.0.dist-info/top_level.txt
cuc_mcp_time_server-0.1.0.dist-info/RECORD
