Metadata-Version: 2.4
Name: cuc-mcp-time-server
Version: 0.1.0
Summary: A Model Context Protocol (MCP) time server that provides current time information
Author-email: Your Name <your.email@example.com>
Project-URL: Homepage, https://github.com/yourusername/mcp-time-server
Project-URL: Repository, https://github.com/yourusername/mcp-time-server
Project-URL: Documentation, https://github.com/yourusername/mcp-time-server/wiki
Classifier: Programming Language :: Python :: 3
Classifier: License :: OSI Approved :: MIT License
Classifier: Operating System :: OS Independent
Classifier: Intended Audience :: Developers
Classifier: Topic :: Software Development :: Libraries :: Python Modules
Requires-Python: >=3.7
License-File: LICENSE
Requires-Dist: pytz>=2021.1
Requires-Dist: fastmcp>=0.1.0
Dynamic: license-file
